jupyterlite/__init__.py
jupyterlite/__main__.py
jupyterlite/constants.py
jupyterlite/addons/base.py
jupyterlite-0.6.4.dist-info/METADATA
jupyterlite-0.6.4.dist-info/WHEEL
jupyterlite-0.6.4.dist-info/licenses/LICENSE
jupyterlite-0.6.4.dist-info/RECORD
