Metadata-Version: 2.4
Name: jupyterlite
Version: 0.6.4
Dynamic: Summary
Project-URL: Source, https://github.com/jupyterlite/jupyterlite
Author: JupyterLite Contributors
License: BSD 3-Clause License
License-File: LICENSE
Keywords: browser,js,jupyter,jupyterlab,notebook,pyodide,schema
Classifier: Development Status :: 4 - Beta
Classifier: Framework :: Jupyter
Classifier: Framework :: Jupyter :: JupyterLab
Classifier: Framework :: Jupyter :: JupyterLab :: 4
Classifier: Intended Audience :: Developers
Classifier: Intended Audience :: Science/Research
Classifier: License :: OSI Approved :: BSD License
Classifier: Programming Language :: Python
Classifier: Programming Language :: Python :: 3 :: Only
Classifier: Programming Language :: Python :: 3.9
Classifier: Programming Language :: Python :: 3.10
Classifier: Programming Language :: Python :: 3.11
Classifier: Programming Language :: Python :: 3.12
Classifier: Programming Language :: Python :: 3.13
Classifier: Topic :: Software Development :: Documentation
Classifier: Topic :: Software Development :: Pre-processors
Classifier: Topic :: Text Processing :: Markup :: HTML
Requires-Python: >=3.9
Requires-Dist: jupyterlite-core>=0.6.4
Provides-Extra: all
Requires-Dist: jsonschema>=3; extra == 'all'
Requires-Dist: jupyter-server; extra == 'all'
Requires-Dist: jupyterlab-server<3,>=2.8.1; extra == 'all'
Requires-Dist: jupyterlab<4.5,>=4.4.5; extra == 'all'
Requires-Dist: libarchive-c>=4.0; extra == 'all'
Requires-Dist: notebook<7.5,>=7.4.5; extra == 'all'
Requires-Dist: pkginfo; extra == 'all'
Requires-Dist: tornado>=6.1; extra == 'all'
Provides-Extra: check
Requires-Dist: jsonschema[format-nongpl]>=3; extra == 'check'
Provides-Extra: contents
Requires-Dist: jupyter-server; extra == 'contents'
Provides-Extra: lab
Requires-Dist: jupyterlab<4.5,>=4.4.5; extra == 'lab'
Requires-Dist: notebook<7.5,>=7.4.5; extra == 'lab'
Provides-Extra: libarchive
Requires-Dist: libarchive-c>=4.0; extra == 'libarchive'
Provides-Extra: serve
Requires-Dist: tornado>=6.1; extra == 'serve'
Provides-Extra: translation
Requires-Dist: jupyterlab-server<3,>=2.8.1; extra == 'translation'
